[
  {
    "id": "1",
    "name": "Sophie Laurent",
    "waste": 342,
    "events": 22,
    "level": 12
  },
  {
    "id": "2",
    "name": "Thomas Moreau",
    "waste": 318,
    "events": 19,
    "level": 11
  },
  {
    "id": "3",
    "name": "Marie Dupont",
    "waste": 245,
    "events": 15,
    "level": 8
  },
  {
    "id": "4",
    "name": "Lucas Bernard",
    "waste": 198,
    "events": 14,
    "level": 7
  },
  {
    "id": "5",
    "name": "Emma Petit",
    "waste": 175,
    "events": 12,
    "level": 7
  }
]
